{"nombre":"enzo","email":"enzo@gmail.com","password":"$2y$10$mzLjqFIR1rAQsFzmDuOqr.SjzeH7fvRniYhTwjfEYyme4cwtYacbe","avatar":"..\/avatars\/avatar2.svg","perfil":"97"}
{"nombre":"enzo","email":"enzo3@gmail.com","password":"$2y$10$8mPRkNir6zsX6NUJZm0Lhun\/.NeP1tyw4E17wnIzzp29AGGIeoRDa","avatar":"..\/avatars\/avatar4.svg","perfil":"1"}
{"nombre":"enzo","email":"enzo6@gmail.com","password":"$2y$10$0vf9LGAgXsE64cOkCFqbQObwSFXZXGgNEpMRrh6yNDEXLdiKq3B62","avatar":"..\/avatars\/avatar8.svg","perfil":"1"}
{"nombre":"enzo","email":"enzo4@gmail.com","password":"$2y$10$GVwj1S0Y4fCxjC7I5asFpejbIaIxj7usNvc47T2\/OBVbUJUGzD2\/i","avatar":"..\/avatars\/avatar3.svg","perfil":"1"}
{"nombre":"gustavo","email":"gusty@dh.com","password":"$2y$10$2WNBV7y5b6OwRVPe2bOZBeu.sKb7BdC331KRt66NCMty4OEU8Druy","avatar":"..\/avatars\/avatar7.svg","perfil":null}
{"nombre":"pau","email":"pau@gmail.com","password":"$2y$10$r2Hq2z4LrnL4l6QVd9lKMuWd4IEGxyh2hwtITavYOsHT4n8Eq2EpG","avatar":"..\/avatars\/avatar4.svg","perfil":"97"}
{"nombre":"gusty","email":"gustavo@gmail.com","password":"$2y$10$MjEOUbM6tW24qW8kgDVOO.l6NxtOPPKbmB6tHvDdN6GlRp2bXu5HW","avatar":"..\/avatars\/avatar3.svg","perfil":"97"}
{"nombre":"pau","email":"pau@pau.com","password":"$2y$10$YRBCda9KAPtBl6tQJqGnF.J0NBoJkqFO7kMNkxxTceGkgr\/I9d0ym","avatar":"..\/avatars\/avatar1.svg","perfil":"1"}
